ANN.py
Advanced_Neural_Network-1.0.2.dist-info/LICENSE.txt
Advanced_Neural_Network-1.0.2.dist-info/METADATA
Advanced_Neural_Network-1.0.2.dist-info/WHEEL
Advanced_Neural_Network-1.0.2.dist-info/top_level.txt
Advanced_Neural_Network-1.0.2.dist-info/RECORD
