Metadata-Version: 2.1
Name: Advanced-Neural-Network
Version: 1.0.2
Summary: Advanced use of neural networks
Home-page: https://github.com/alix59/NN
Author: Hamidou Alix
Author-email: alix.hamidou@gmail.com
License: UNKNOWN
Platform: UNKNOWN
Classifier: Programming Language :: Python :: 3
Classifier: Programming Language :: Python :: 3.6
Classifier: Programming Language :: Python :: 3.8
Classifier: Intended Audience :: Developers
Classifier: Intended Audience :: Science/Research
Classifier: License :: OSI Approved :: GNU General Public License v2 or later (GPLv2+)
Classifier: Operating System :: Microsoft :: Windows
Classifier: Operating System :: Unix
Provides-Extra: dev
Requires-Dist: pytest (>=3.7) ; extra == 'dev'
